mjml/__init__.py
mjml/_types.py
mjml/mjml2html.py
mjml/testing_helpers.py
mjml/core/__init__.py
mjml/core/api.py
mjml/core/registry.py
mjml/elements/__init__.py
mjml/elements/_accordion_helpers.py
mjml/elements/_base.py
mjml/elements/mj_accordion.py
mjml/elements/mj_accordion_element.py
mjml/elements/mj_accordion_text.py
mjml/elements/mj_accordion_title.py
mjml/elements/mj_body.py
mjml/elements/mj_button.py
mjml/elements/mj_carousel.py
mjml/elements/mj_carousel_image.py
mjml/elements/mj_column.py
mjml/elements/mj_divider.py
mjml/elements/mj_group.py
mjml/elements/mj_hero.py
mjml/elements/mj_image.py
mjml/elements/mj_navbar.py
mjml/elements/mj_navbar_link.py
mjml/elements/mj_raw.py
mjml/elements/mj_section.py
mjml/elements/mj_social.py
mjml/elements/mj_social_element.py
mjml/elements/mj_spacer.py
mjml/elements/mj_table.py
mjml/elements/mj_text.py
mjml/elements/mj_wrapper.py
mjml/elements/head/__init__.py
mjml/elements/head/_head_base.py
mjml/elements/head/mj_attributes.py
mjml/elements/head/mj_breakpoint.py
mjml/elements/head/mj_font.py
mjml/elements/head/mj_head.py
mjml/elements/head/mj_html_attributes.py
mjml/elements/head/mj_preview.py
mjml/elements/head/mj_style.py
mjml/elements/head/mj_title.py
mjml/helpers/__init__.py
mjml/helpers/conditional_tag.py
mjml/helpers/fonts.py
mjml/helpers/json_to_xml.py
mjml/helpers/make_lower_breakpoint.py
mjml/helpers/media_queries.py
mjml/helpers/mergeOutlookConditionals.py
mjml/helpers/preview.py
mjml/helpers/py_utils.py
mjml/helpers/shorthand_parser.py
mjml/helpers/skeleton.py
mjml/helpers/suffixCssClasses.py
mjml/helpers/width_parser.py
mjml/lib/__init__.py
mjml/lib/dict_merger.py
mjml/lib/tests/__init__.py
mjml/lib/tests/dict_merger_test.py
mjml/scripts/__init__.py
mjml/scripts/mjml-html-compare
mjml/scripts/mjml.py
mjml-0.12.0.data/scripts/mjml-html-compare
mjml-0.12.0.dist-info/licenses/LICENSE.txt
mjml-0.12.0.dist-info/METADATA
mjml-0.12.0.dist-info/WHEEL
mjml-0.12.0.dist-info/entry_points.txt
mjml-0.12.0.dist-info/top_level.txt
mjml-0.12.0.dist-info/zip-safe
mjml-0.12.0.dist-info/RECORD
