Metadata-Version: 2.4
Name: mjml
Version: 0.12.0
Summary: Python implementation for MJML - a framework that makes responsive-email easy
Home-page: https://github.com/FelixSchwarz/mjml-python
Author: Felix Schwarz
Author-email: felix.schwarz@oss.schwarz.eu
License: MIT
Project-URL: Code, https://github.com/FelixSchwarz/mjml-python
Project-URL: Issue tracker, https://github.com/FelixSchwarz/mjml-python/issues
Classifier: Development Status :: 4 - Beta
Classifier: Intended Audience :: Developers
Classifier: License :: OSI Approved :: MIT License
Classifier: Programming Language :: Python :: 3
Classifier: Programming Language :: Python :: 3.9
Classifier: Programming Language :: Python :: 3.10
Classifier: Programming Language :: Python :: 3.11
Classifier: Programming Language :: Python :: 3.12
Classifier: Programming Language :: Python :: 3.13
Classifier: Programming Language :: Python :: 3.14
Classifier: Topic :: Communications :: Email
Classifier: Topic :: Text Processing :: Markup :: HTML
Requires-Python: >=3.9
License-File: LICENSE.txt
Requires-Dist: beautifulsoup4
Requires-Dist: dotmap
Requires-Dist: docopt-ng
Requires-Dist: jinja2
Requires-Dist: typing_extensions
Provides-Extra: testing
Requires-Dist: HTMLCompare>=0.4.0; extra == "testing"
Requires-Dist: lxml; extra == "testing"
Requires-Dist: pytest; extra == "testing"
Provides-Extra: css-inlining
Requires-Dist: css_inline>=0.11; extra == "css-inlining"
Dynamic: license-file
